macrometa_source_mssql/__init__.py
macrometa_source_mssql/connection.py
macrometa_source_mssql/sample_data.py
macrometa_source_mssql/sync_strategies/__init__.py
macrometa_source_mssql/sync_strategies/common.py
macrometa_source_mssql/sync_strategies/full_table.py
macrometa_source_mssql/sync_strategies/log_based.py
macrometa_source_mssql-1.0.0.dist-info/entry_points.txt
macrometa_source_mssql-1.0.0.dist-info/LICENSE
macrometa_source_mssql-1.0.0.dist-info/WHEEL
macrometa_source_mssql-1.0.0.dist-info/METADATA
macrometa_source_mssql-1.0.0.dist-info/RECORD
