Metadata-Version: 2.1
Name: macrometa-source-mssql
Version: 1.0.0
Summary: Macrometa Source for extracting data from Microsoft SQL Server.
License: Apache-2.0
Keywords: ELT,Connectors,Workflows,Macrometa,MSSQL,Microsoft SQL Server,Source
Author: Macrometa
Author-email: info@macrometa.com
Requires-Python: >=3.8.1,<3.11
Classifier: License :: OSI Approved :: Apache Software License
Classifier: Programming Language :: Python :: 3
Classifier: Programming Language :: Python :: 3.9
Classifier: Programming Language :: Python :: 3.10
Classifier: Programming Language :: Python :: 3 :: Only
Classifier: Programming Language :: Python :: 3.8
Requires-Dist: attrs (>=16.3.0)
Requires-Dist: c8connector (>=0.0.24)
Requires-Dist: pendulum (>=1.2.0)
Requires-Dist: pipelinewise-singer-python (==1.2.0)
Requires-Dist: prometheus-client (==0.16.0)
Requires-Dist: pymssql (>=2.2.1)
Project-URL: Bug Tracker, https://github.com/Macrometacorp/macrometa-source-mssql/issues
